mridumanda_shvedt/__about__.py
mridumanda_shvedt/__init__.py
mridumanda_shvedt/__main__.py
mridumanda_shvedt/weather.py
mridumanda_shvedt/weather_ascii.py
mridumanda_shvedt-1.6.dist-info/METADATA
mridumanda_shvedt-1.6.dist-info/WHEEL
mridumanda_shvedt-1.6.dist-info/entry_points.txt
mridumanda_shvedt-1.6.dist-info/licenses/LICENSE
mridumanda_shvedt-1.6.dist-info/RECORD
