Metadata-Version: 2.3
Name: mridumanda_shvedt
Version: 1.6
Summary: A minimal console based weather application.
Project-URL: Documentation, https://github.com/shvedt/mridu-manda/blob/main/README.md
Project-URL: Issues, https://github.com/shvedt/mridu-manda/issues
Project-URL: Source, https://github.com/shvedt/mridu-manda
Author-email: Shvetank Dattatreya <dshvetank@gmail.com>
License-Expression: GPL-3.0
License-File: LICENSE
Classifier: Development Status :: 4 - Beta
Classifier: Programming Language :: Python
Classifier: Programming Language :: Python :: 3.8
Classifier: Programming Language :: Python :: 3.9
Classifier: Programming Language :: Python :: 3.10
Classifier: Programming Language :: Python :: 3.11
Classifier: Programming Language :: Python :: 3.12
Classifier: Programming Language :: Python :: Implementation :: CPython
Classifier: Programming Language :: Python :: Implementation :: PyPy
Requires-Python: >=3.8
Requires-Dist: requests>=2.31.0
Requires-Dist: rich>=13.8.0
